CHANGES.rst
CONTRIBUTORS.rst
MANIFEST.in
README.rst
setup.py
collective/__init__.py
collective.recipe.pip.egg-info/PKG-INFO
collective.recipe.pip.egg-info/SOURCES.txt
collective.recipe.pip.egg-info/dependency_links.txt
collective.recipe.pip.egg-info/entry_points.txt
collective.recipe.pip.egg-info/namespace_packages.txt
collective.recipe.pip.egg-info/not-zip-safe
collective.recipe.pip.egg-info/pbr.json
collective.recipe.pip.egg-info/requires.txt
collective.recipe.pip.egg-info/top_level.txt
collective/recipe/__init__.py
collective/recipe/pip/__init__.py
collective/recipe/pip/testing/__init__.py
collective/recipe/pip/testing/test_docs.py