Metadata-Version: 1.1
Name: collective.recipe.pip
Version: 0.3.3
Summary: zc.buildout recipe to parse pip config files ang use parsed info in a buildout.
Home-page: http://github.com/collective/collective.recipe.pip
Author: Anatoly Bubenkov
Author-email: bubenkoff@gmail.com
License: GPL
Keywords: zc.buildout buildout recipe
Platform: UNKNOWN
Classifier: Framework :: Buildout
Classifier: Intended Audience :: Developers
Classifier: Topic :: Software Development :: Build Tools
Classifier: License :: OSI Approved :: GNU General Public License (GPL)
